mtube_algorithm/app.py
wootube-0.0.1.dist-info/METADATA
wootube-0.0.1.dist-info/WHEEL
wootube-0.0.1.dist-info/top_level.txt
wootube-0.0.1.dist-info/RECORD
