Metadata-Version: 2.1
Name: wootube
Version: 0.0.1
Summary: wootube sulmyeong
Author: WooSH
